{"pageProps":{"post":{"id":"I_kwDOD_pKSM5Hig5c","url":"https://github.com/xiaotiandada/blog/issues/98","title":"Keyboard API","updatedAt":"2022-04-11T16:34:09Z","createdAt":"2022-04-11T16:33:52Z","body":"- https://developer.mozilla.org/en-US/docs/Web/API/Keyboard/lock","comments":{"nodes":[]},"reactionGroups":[{"content":"THUMBS_UP","reactors":{"totalCount":0}},{"content":"THUMBS_DOWN","reactors":{"totalCount":0}},{"content":"LAUGH","reactors":{"totalCount":0}},{"content":"HOORAY","reactors":{"totalCount":0}},{"content":"CONFUSED","reactors":{"totalCount":0}},{"content":"HEART","reactors":{"totalCount":0}},{"content":"ROCKET","reactors":{"totalCount":0}},{"content":"EYES","reactors":{"totalCount":0}}],"author":{"login":"xiaotiandada","url":"https://github.com/xiaotiandada","avatarUrl":"https://avatars.githubusercontent.com/u/24250627?u=51a93e07957381123eb9fbdd6407de36033b578d&v=4"},"html":"<ul>\n<li><a href=\"https://developer.mozilla.org/en-US/docs/Web/API/Keyboard/lock\">https://developer.mozilla.org/en-US/docs/Web/API/Keyboard/lock</a></li>\n</ul>\n","attributes":{}},"themeConfig":{"title":"Blog(issues)","links":[{"title":"GitHub","url":"https://github.com/xiaotiandada/blog"},{"title":"Twitter","url":"https://twitter.com/XiaoTianIsMe"}]}},"__N_SSG":true}